MANIFEST.in
README.md
setup.py
gradepy/__init__.py
gradepy/command_line.py
gradepy/grade.py
gradepy/makecsv.py
gradepy.egg-info/PKG-INFO
gradepy.egg-info/SOURCES.txt
gradepy.egg-info/dependency_links.txt
gradepy.egg-info/not-zip-safe
gradepy.egg-info/top_level.txt