Metadata-Version: 1.0
Name: gradepy
Version: 0.3
Summary: Tools for automated grading of python assignments.
Home-page: https://github.com/fredcallaway/grade.py
Author: Fred Callaway
Author-email: fredc@llaway.com
License: MIT
Keywords: grade grading python framework student assignment
Platform: UNKNOWN
